{
  "name": "PCKG_INV_TRACKER",
  "type": "PACKAGE BODY",
  "line_count": 537,
  "tables_referenced": [
    "RMA_INWARD_DET",
    "INVOICE_MT",
    "ADVANCE_SALES_ORDER_MT",
    "DISPATCH_ADVICE_MT",
    "DC_MT",
    "SALES_ORDER_DET"
  ],
  "body_snippet": "package body pckg_inv_tracker IS\n\n  TYPE REC_NUM IS RECORD(ID NUMBER,DET_ID NUMBER);\n  TYPE TAB_NUM IS TABLE OF REC_NUM INDEX BY BINARY_INTEGER ;       \n  \n  FUNCTION populate_temp_inv_trk(parm_Doc_typ VARCHAR2,track_type VARCHAR2,parm_id number,parm_det_id NUMBER,parm_parent_track_id NUMBER) RETURN NUMBER ;\n  FUNCTION GET_COMPLETE_WHERE (PARM_INV_BOOK_ID NUMBER,PARM_INV_BOOK_COL_NAME VARCHAR2,PARM_CUSTOMER_ID NUMBER,PARM_CUSTOMER_COL_NAME VARCHAR2 ,PARM_SUPPLIER_ID NUMBER,PARM_SUPPLIER_COL_NAME VARCHAR2, PARM_FROM_ITEM VARCHAR2,PARM_TO_ITEM VARCHAR2,PARM_ITEM_COL_NAME VARCHAR2,PARM_FROM_DOC_NO NUMBER,PARM_TO_DOC_NO NUMBER,PARM_DOC_NO_COL_NAME VARCHAR2,PARM_FROM_DOC_DATE DATE,PARM_TO_DOC_DATE DATE, PARM_DOC_DATE_COL_NAME VARCHAR2,PARM_FROM_REF_NO VARCHAR2,PARM_TO_REF_NO VARCHAR2,PARM_REF_NO_COL_NAME VARCHAR2) RETURN VARCHAR2 ;\n  FUNCTION GET_SQL_RESULT (PARM_QRY VARCHAR2) RETURN TAB_NUM ;\n  \n  lgnum_temp_tab_id NUMBER:=0;\n  \n  PROCEDURE POPULATE(PARM_DOC_TYPE VARCHAR2,PARM_TRACK_TYPE VARCHAR2,PARM_INV_BOOK_ID NUMBER,PARM_CUSTOMER_ID NUMBER ,PARM_SUPPLIER_ID NUMBER, PARM_FROM_ITEM VARCHAR2,PARM_TO_ITEM VARCHAR2,PARM_FROM_DOC_NO NUMBER,PARM_TO_DOC_NO NUMBER,PARM_FROM_DOC_DATE DATE,PARM_TO_DOC_DATE DATE ,PARM_FROM_REF_NO VARCHAR2,PARM_TO_REF_NO VARCHAR2) IS \n       LVCH_WHERE VARCHAR2(500);\n       LVCH_QRY   VARCHAR2(1000);\n       LTAB_QRY_RESULT TAB_NUM;\n       lnum_temp NUMBER;\n  BEGIN\n       \n       DELETE TEMP_INVENTORY_TRACKER;\n       \n       IF PARM_DOC_TYPE = 'ASO' THEN \n"
}